mundipy/api/__init__.py
mundipy/cache/__init__.py
mundipy/dataset.py
mundipy/geometry.py
mundipy/map.py
mundipy/mundi.py
mundipy/pcs/README.md
mundipy/pcs/__init__.py
mundipy/pcs/_simplify.py
mundipy/pcs/crs_enhanced.fgb
mundipy/utils.py
mundipy-0.8.2.dist-info/LICENSE
mundipy-0.8.2.dist-info/WHEEL
mundipy-0.8.2.dist-info/METADATA
mundipy-0.8.2.dist-info/RECORD
