Metadata-Version: 2.1
Name: mundipy
Version: 0.8.2
Summary: mundipy is a Python framework for spatial data analysis
Home-page: https://buntinglabs.com/
License: MIT
Author: Brendan Ashworth
Author-email: brendan@buntinglabs.com
Requires-Python: >=3.8,<4.0
Classifier: License :: OSI Approved :: MIT License
Classifier: Operating System :: OS Independent
Classifier: Programming Language :: Python :: 3
Classifier: Programming Language :: Python :: 3.8
Classifier: Programming Language :: Python :: 3.9
Classifier: Programming Language :: Python :: 3.10
Classifier: Programming Language :: Python :: 3.11
Classifier: Programming Language :: Python :: 3
Classifier: Topic :: Scientific/Engineering :: GIS
Requires-Dist: Fiona (>=1.8.21,<2.0.0)
Requires-Dist: SQLAlchemy (>=1.4.40,<2.0.0)
Requires-Dist: fiona (>=1.8.21,<2.0.0)
Requires-Dist: numpy (>=1.23.3,<2.0.0)
Requires-Dist: psycopg (>=3.0.16,<4.0.0)
Requires-Dist: psycopg-binary (>=3.0.16,<4.0.0)
Requires-Dist: psycopg-pool (>=3.1.1,<4.0.0)
Requires-Dist: pyproj (>=3.4.0,<4.0.0)
Requires-Dist: shapely (==2.0b2)
Requires-Dist: tqdm (>=4.64.1,<5.0.0)
Project-URL: Documentation, https://docs.mundi.ai/
Project-URL: Repository, https://github.com/BuntingLabs/mundipy
